.gitattributes
.gitignore
LICENSE.txt
README.md
pyproject.toml
requirements.txt
vanilla_option_pricers/__init__.py
vanilla_option_pricers/bachelier.py
vanilla_option_pricers/black_scholes.py
vanilla_option_pricers/utils.py
vanilla_option_pricers.egg-info/PKG-INFO
vanilla_option_pricers.egg-info/SOURCES.txt
vanilla_option_pricers.egg-info/dependency_links.txt
vanilla_option_pricers.egg-info/requires.txt
vanilla_option_pricers.egg-info/top_level.txt
vanilla_option_pricers/tests/__init__.py
vanilla_option_pricers/tests/bsm_speed.py