Metadata-Version: 2.4
Name: vanilla-option-pricers
Version: 1.2.1
Summary: Fast and vectorised pricer and implied volatility fitters for Black-Scholes and Merton models
Author-email: Artur Sepp <artursepp@gmail.com>
Maintainer-email: Artur Sepp <artursepp@gmail.com>
License: GNU GENERAL PUBLIC LICENSE
Project-URL: Homepage, https://github.com/ArturSepp/VanillaOptionPricers
Project-URL: Documentation, https://github.com/ArturSepp/VanillaOptionPricers/blob/main/README.md
Project-URL: Repository, https://github.com/ArturSepp/VanillaOptionPricers.git
Project-URL: Issues, https://github.com/ArturSepp/VanillaOptionPricers/issues
Project-URL: Changelog, https://github.com/ArturSepp/VanillaOptionPricers/blob/main/CHANGELOG.md
Project-URL: PyPI, https://pypi.org/project/vanilla-option-pricers/
Keywords: option pricing,black-scholes,merton model,implied volatility,vanilla options,financial derivatives,quantitative finance,fast pricing,vectorised computation,options analytics,mathematical finance,european options,american options,option greeks,risk management,numba optimization
Classifier: Development Status :: 4 - Beta
Classifier: Intended Audience :: Developers
Classifier: Intended Audience :: Financial and Insurance Industry
Classifier: Intended Audience :: Science/Research
Classifier: License :: OSI Approved :: GNU General Public License v3 or later (GPLv3+)
Classifier: Operating System :: OS Independent
Classifier: Programming Language :: Python
Classifier: Programming Language :: Python :: 3
Classifier: Programming Language :: Python :: 3.8
Classifier: Programming Language :: Python :: 3.9
Classifier: Programming Language :: Python :: 3.10
Classifier: Programming Language :: Python :: 3.11
Classifier: Programming Language :: Python :: 3.12
Classifier: Programming Language :: Python :: 3.13
Classifier: Topic :: Office/Business :: Financial :: Investment
Classifier: Topic :: Scientific/Engineering :: Mathematics
Classifier: Topic :: Scientific/Engineering :: Information Analysis
Classifier: Topic :: Software Development :: Libraries :: Python Modules
Requires-Python: >=3.8
License-File: LICENSE.txt
Requires-Dist: numba>=0.60.0
Requires-Dist: numpy==2.2.6
Provides-Extra: analytics
Requires-Dist: pandas>=2.3.1; extra == "analytics"
Requires-Dist: statsmodels>=0.14.0; extra == "analytics"
Provides-Extra: reports
Requires-Dist: pybloqs>=1.2.13; extra == "reports"
Requires-Dist: jinja2>=3.0.0; extra == "reports"
Requires-Dist: openpyxl>=3.1.0; extra == "reports"
Requires-Dist: tabulate>=0.9.0; extra == "reports"
Provides-Extra: visualization
Requires-Dist: matplotlib>=3.9.0; extra == "visualization"
Requires-Dist: seaborn>=0.13.0; extra == "visualization"
Requires-Dist: plotly>=5.0.0; extra == "visualization"
Provides-Extra: jupyter
Requires-Dist: jupyter>=1.0.0; extra == "jupyter"
Requires-Dist: notebook>=6.5.0; extra == "jupyter"
Requires-Dist: jupyterlab>=3.0.0; extra == "jupyter"
Requires-Dist: ipykernel>=6.0.0; extra == "jupyter"
Requires-Dist: ipywidgets>=8.0.0; extra == "jupyter"
Provides-Extra: dev
Requires-Dist: pytest>=7.0.0; extra == "dev"
Requires-Dist: pytest-cov>=4.0.0; extra == "dev"
Requires-Dist: pytest-mock>=3.10.0; extra == "dev"
Requires-Dist: pytest-xdist>=3.0.0; extra == "dev"
Requires-Dist: black>=22.0.0; extra == "dev"
Requires-Dist: flake8>=5.0.0; extra == "dev"
Requires-Dist: mypy>=1.0.0; extra == "dev"
Requires-Dist: isort>=5.10.0; extra == "dev"
Requires-Dist: pre-commit>=3.0.0; extra == "dev"
Provides-Extra: performance
Requires-Dist: memory-profiler>=0.60.0; extra == "performance"
Requires-Dist: line-profiler>=4.0.0; extra == "performance"
Requires-Dist: py-spy>=0.3.0; extra == "performance"
Requires-Dist: scalene>=1.5.0; extra == "performance"
Provides-Extra: database
Requires-Dist: SQLAlchemy>=2.0.0; extra == "database"
Requires-Dist: psycopg2>=2.9.5; extra == "database"
Requires-Dist: pyarrow>=18.0.0; extra == "database"
Requires-Dist: fsspec>=2024.12.0; extra == "database"
Provides-Extra: finance
Requires-Dist: qis>=3.2.22; extra == "finance"
Requires-Dist: yfinance>=0.2.65; extra == "finance"
Requires-Dist: pandas-datareader>=0.10.0; extra == "finance"
Provides-Extra: all
Requires-Dist: vanilla-option-pricers[analytics,database,finance,jupyter,performance,reports,visualization]; extra == "all"
Provides-Extra: extras
Requires-Dist: vanilla-option-pricers[analytics,visualization]; extra == "extras"
Dynamic: license-file
